{
  "trump": 22,
  "iran": 20,
  "talks": 12,
  "hormuz": 10,
  "fire": 8,
  "vance": 8,
  "off": 7,
  "lebanon": 7,
  "strait": 6,
  "starmer": 6,
  "switzerland": 5,
  "ceasefire": 5,
  "reflecting": 5,
  "pool": 5,
  "here": 5,
  "ukraine": 5,
  "russia": 5,
  "say": 5,
  "prime": 5,
  "apple": 5,
  "presidential": 5,
  "strikes": 4,
  "deal": 4,
  "strike": 4,
  "its": 4,
  "day": 4,
  "boyle": 4,
  "heights": 4,
  "oil": 4,
  "down": 4,
  "live": 4,
  "closed": 3,
  "israeli": 3,
  "hikers": 3,
  "die": 3,
  "grand": 3,
  "canyon": 3,
  "olympian": 3,
  "obama": 3,
  "center": 3,
  "spacex": 3,
  "warsh": 3,
  "deals": 3,
  "continues": 3,
  "emergency": 3,
  "let": 3,
  "peace": 3,
  "heat": 3,
  "again": 3,
  "running": 3
}