{
  "trump": 103,
  "ukraine": 29,
  "military": 28,
  "rfk": 25,
  "navy": 25,
  "war": 24,
  "tech": 22,
  "jobs": 22,
  "fed": 21,
  "senate": 21,
  "white": 20,
  "house": 20,
  "lisbon": 20,
  "funding": 19,
  "streetcar": 19,
  "troops": 18,
  "resigns": 18,
  "lenovo": 18,
  "crash": 16,
  "rebrand": 16,
  "killed": 15,
  "defense": 15,
  "musk": 15,
  "dinner": 15,
  "north": 15,
  "pentagon": 15,
  "immigration": 15,
  "hearing": 15,
  "legion": 15,
  "senators": 14,
  "postwar": 14,
  "florida": 13,
  "its": 13,
  "macron": 13,
  "major": 13,
  "raid": 13,
  "force": 12,
  "afghanistan": 12,
  "first": 12,
  "republicans": 12,
  "doj": 12,
  "moments": 12,
  "contentious": 12,
  "tesla": 12,
  "thailand": 12,
  "hyundai": 12,
  "murder": 12,
  "northwestern": 11,
  "earthquake": 11,
  "elon": 11
}