{
  "trump": 33,
  "iran": 22,
  "spirit": 16,
  "airlines": 15,
  "war": 11,
  "oil": 10,
  "down": 10,
  "germany": 9,
  "prices": 8,
  "berkshire": 8,
  "day": 7,
  "abortion": 7,
  "terminated": 6,
  "house": 6,
  "first": 6,
  "rescue": 6,
  "have": 6,
  "deal": 6,
  "ruling": 6,
  "gas": 6,
  "congress": 5,
  "states": 5,
  "alabama": 5,
  "apple": 5,
  "musk": 5,
  "abel": 5,
  "deadline": 4,
  "video": 4,
  "correspondents": 4,
  "dinner": 4,
  "supreme": 4,
  "congressman": 4,
  "venezuela": 4,
  "know": 4,
  "record": 4,
  "live": 4,
  "its": 4,
  "hostilities": 4,
  "access": 4,
  "across": 4,
  "troops": 4,
  "ukraine": 4,
  "through": 4,
  "operations": 4,
  "into": 4,
  "iranian": 4,
  "cash": 4,
  "greg": 4,
  "ceo": 4,
  "buffett": 4
}