{
  "kirk": 88,
  "trump": 78,
  "charlie": 74,
  "fed": 42,
  "china": 36,
  "russian": 34,
  "israel": 34,
  "shooting": 32,
  "iphone": 31,
  "qatar": 30,
  "governor": 29,
  "nato": 26,
  "gaza": 23,
  "launches": 23,
  "records": 22,
  "political": 21,
  "drone": 20,
  "apple": 20,
  "oil": 19,
  "strikes": 19,
  "air": 19,
  "million": 18,
  "its": 18,
  "london": 17,
  "far": 17,
  "right": 17,
  "rubio": 17,
  "breaks": 17,
  "killing": 16,
  "utah": 16,
  "comments": 16,
  "end": 16,
  "house": 16,
  "romania": 16,
  "death": 16,
  "rally": 15,
  "strike": 15,
  "electric": 15,
  "sanctions": 15,
  "administration": 15,
  "cook": 15,
  "white": 15,
  "people": 15,
  "out": 15,
  "ramps": 14,
  "seeks": 14,
  "airspace": 14,
  "high": 14,
  "preorders": 14,
  "before": 14
}