{
  "trump": 22,
  "iran": 19,
  "israel": 15,
  "live": 10,
  "strikes": 10,
  "election": 8,
  "korea": 8,
  "south": 6,
  "earthquake": 6,
  "philippines": 6,
  "interview": 5,
  "war": 5,
  "spacex": 5,
  "apple": 5,
  "pratt": 5,
  "oil": 5,
  "launches": 4,
  "walks": 4,
  "out": 4,
  "platner": 4,
  "back": 4,
  "least": 4,
  "hits": 4,
  "off": 4,
  "stock": 4,
  "fire": 4,
  "york": 4,
  "penn": 4,
  "station": 4,
  "north": 4,
  "tsunami": 4,
  "nbc": 4,
  "spencer": 4,
  "people": 4,
  "pope": 4,
  "siri": 4,
  "here": 4,
  "ipo": 4,
  "ios": 4,
  "missiles": 3,
  "meet": 3,
  "ukraine": 3,
  "talks": 3,
  "ohio": 3,
  "festival": 3,
  "gunmen": 3,
  "hopes": 3,
  "close": 3,
  "months": 3,
  "sink": 3
}