{
  "iran": 86,
  "trump": 56,
  "oil": 50,
  "war": 46,
  "apple": 22,
  "prices": 22,
  "killed": 21,
  "say": 20,
  "live": 19,
  "iranian": 18,
  "east": 15,
  "wants": 14,
  "take": 13,
  "middle": 13,
  "fuel": 12,
  "these": 12,
  "election": 12,
  "hormuz": 12,
  "dow": 12,
  "another": 12,
  "stock": 12,
  "out": 11,
  "strikes": 11,
  "hit": 11,
  "gulf": 11,
  "shot": 11,
  "ukraine": 11,
  "bases": 11,
  "while": 10,
  "israel": 10,
  "elections": 10,
  "targets": 10,
  "tumble": 10,
  "barrel": 10,
  "market": 10,
  "markets": 9,
  "samsung": 9,
  "video": 9,
  "economy": 9,
  "latest": 9,
  "teacher": 9,
  "states": 9,
  "prime": 9,
  "pennsylvania": 9,
  "trooper": 9,
  "here": 8,
  "energy": 8,
  "ultra": 8,
  "scoop": 8,
  "dismayed": 8
}